SMOF_MOF/__init__.py
SMOF_MOF/main.py
SMOF_MOF-0.3.dist-info/License.txt
SMOF_MOF-0.3.dist-info/METADATA
SMOF_MOF-0.3.dist-info/WHEEL
SMOF_MOF-0.3.dist-info/top_level.txt
SMOF_MOF-0.3.dist-info/RECORD
