Metadata-Version: 2.1
Name: SMOF-MOF
Version: 0.3
Summary: UNKNOWN
Home-page: UNKNOWN
License: UNKNOWN
Platform: UNKNOWN
Requires-Dist: numpy (>=1.23)
Requires-Dist: numba (>=0.56.0)
Requires-Dist: scipy (>=1.8.0)
Requires-Dist: scikit-learn (>=1.2.0)
Requires-Dist: tqdm (>=4.64.0)
